CyVer/__init__.py
CyVer/utils.py
CyVer/validators/__init__.py
CyVer/validators/properties_validator.py
CyVer/validators/schema_validator.py
CyVer/validators/syntax_validator.py
cyver-2.0.2.dist-info/licenses/LICENSE
cyver-2.0.2.dist-info/METADATA
cyver-2.0.2.dist-info/WHEEL
cyver-2.0.2.dist-info/top_level.txt
cyver-2.0.2.dist-info/RECORD
