Metadata-Version: 2.4
Name: CyVer
Version: 2.0.2
Summary: Cypher queries Validators against a given Knowledge Graph schema, in terms of syntax, schema validity, and property access.
Home-page: https://gitlab.com/netmode/CyVer
Author: ['Ioanna Mandilara', 'Christina Maria Androna']
Author-email: Ioanna Mandilara <ioanna_mandilara@yahoo.gr>, Christina-Maria Androna <androna.xm@gmail.com>
License: Creative Commons Attribution-ShareAlike 4.0 International (CC BY-SA 4.0) License
Project-URL: Homepage, https://gitlab.com/netmode/CyVer
Project-URL: Documentation, https://gitlab.com/netmode/CyVer/-/wikis/CyVer-Documentation
Project-URL: Changelog, https://gitlab.com/netmode/CyVer/-/blob/main/CHANGELOG.md
Project-URL: Issues, https://gitlab.com/netmode/CyVer/-/issues
Project-URL: Repository, https://gitlab.com/netmode/CyVer
Classifier: Programming Language :: Python :: 3
Classifier: Operating System :: OS Independent
Requires-Python: >=3.10
License-File: LICENSE
Requires-Dist: regex>=2024.11.6
Requires-Dist: neo4j>=5.27
Requires-Dist: pandas>=2.2.3
Dynamic: author
Dynamic: home-page
Dynamic: license-file
Dynamic: requires-python
